sine.event-0.0.1-py2.7-nspkg.pth
sine/event/EventManager.py
sine/event/__init__.py
sine/event/__version__.py
sine/event/tests.py
sine.event-0.0.1.dist-info/DESCRIPTION.rst
sine.event-0.0.1.dist-info/METADATA
sine.event-0.0.1.dist-info/RECORD
sine.event-0.0.1.dist-info/WHEEL
sine.event-0.0.1.dist-info/metadata.json
sine.event-0.0.1.dist-info/namespace_packages.txt
sine.event-0.0.1.dist-info/top_level.txt
